{"trial_1": {"paper": {"colors": "green", "scenes": "kitchen"}, "trial_times": {"object_appear": "2026-03-14_18-50-44.011", "object_disappear": "2026-03-14_18-50-47.024", "scenes_question_appear": "2026-03-14_18-50-50.043", "scenes_answer_time": "2026-03-14_18-50-51.226", "colors_question_appear": "2026-03-14_18-50-53.241", "colors_answer_time": "2026-03-14_18-50-54.064"}}, "trial_2": {"gloves": {"colors": "yellow", "scenes": "living_room"}, "trial_times": {"object_appear": "2026-03-14_18-50-56.084", "object_disappear": "2026-03-14_18-50-59.097", "scenes_question_appear": "2026-03-14_18-51-02.114", "scenes_answer_time": "2026-03-14_18-51-03.412", "colors_question_appear": "2026-03-14_18-51-05.428", "colors_answer_time": "2026-03-14_18-51-06.366"}}, "trial_3": {"sock": {"colors": "yellow", "scenes": "kitchen"}, "trial_times": {"object_appear": "2026-03-14_18-51-08.391", "object_disappear": "2026-03-14_18-51-11.404", "colors_question_appear": "2026-03-14_18-51-14.421", "colors_answer_time": "2026-03-14_18-51-15.207", "scenes_question_appear": "2026-03-14_18-51-17.222", "scenes_answer_time": "2026-03-14_18-51-18.200"}}, "trial_4": {"brush": {"colors": "yellow", "scenes": "kitchen"}, "trial_times": {"object_appear": "2026-03-14_18-51-20.225", "object_disappear": "2026-03-14_18-51-23.239", "colors_question_appear": "2026-03-14_18-51-26.256", "colors_answer_time": "2026-03-14_18-51-26.955", "scenes_question_appear": "2026-03-14_18-51-28.970", "scenes_answer_time": "2026-03-14_18-51-29.495"}}, "trial_5": {"bulb": {"colors": "red", "scenes": "living_room"}, "trial_times": {"object_appear": "2026-03-14_18-51-31.521", "object_disappear": "2026-03-14_18-51-34.534", "colors_question_appear": "2026-03-14_18-51-37.551", "colors_answer_time": "2026-03-14_18-51-38.189", "scenes_question_appear": "2026-03-14_18-51-40.204", "scenes_answer_time": "2026-03-14_18-51-41.255"}}, "trial_6": {"man": {"colors": "green", "scenes": "bathroom"}, "trial_times": {"object_appear": "2026-03-14_18-51-43.282", "object_disappear": "2026-03-14_18-51-46.294", "colors_question_appear": "2026-03-14_18-51-49.313", "colors_answer_time": "2026-03-14_18-51-49.780", "scenes_question_appear": "2026-03-14_18-51-51.795", "scenes_answer_time": "2026-03-14_18-51-52.618"}}, "trial_7": {"mog": {"colors": "green", "scenes": "kitchen"}, "trial_times": {"object_appear": "2026-03-14_18-51-54.643", "object_disappear": "2026-03-14_18-51-57.657", "colors_question_appear": "2026-03-14_18-52-00.674", "colors_answer_time": "2026-03-14_18-52-01.976", "scenes_question_appear": "2026-03-14_18-52-03.993", "scenes_answer_time": "2026-03-14_18-52-06.525"}}, "trial_8": {"chair": {"colors": "red", "scenes": "kitchen"}, "trial_times": {"object_appear": "2026-03-14_18-52-08.552", "object_disappear": "2026-03-14_18-52-11.565", "colors_question_appear": "2026-03-14_18-52-14.582", "colors_answer_time": "2026-03-14_18-52-15.440", "scenes_question_appear": "2026-03-14_18-52-17.455", "scenes_answer_time": "2026-03-14_18-52-18.698"}}, "trial_9": {"tie": {"colors": "green", "scenes": "bathroom"}, "trial_times": {"object_appear": "2026-03-14_18-52-20.719", "object_disappear": "2026-03-14_18-52-23.732", "scenes_question_appear": "2026-03-14_18-52-26.750", "scenes_answer_time": "2026-03-14_18-52-27.841", "colors_question_appear": "2026-03-14_18-52-29.856", "colors_answer_time": "2026-03-14_18-52-30.328"}}, "trial_10": {"lego": {"colors": "red", "scenes": "living_room"}, "trial_times": {"object_appear": "2026-03-14_18-55-48.946", "object_disappear": "2026-03-14_18-55-51.959", "colors_question_appear": "2026-03-14_18-55-54.977", "colors_answer_time": "2026-03-14_18-55-58.263", "scenes_question_appear": "2026-03-14_18-56-00.280", "scenes_answer_time": "2026-03-14_18-56-01.074"}}, "trial_11": {"dustpan": {"colors": "red", "scenes": "bathroom"}, "trial_times": {"object_appear": "2026-03-14_18-56-03.100", "object_disappear": "2026-03-14_18-56-06.113", "scenes_question_appear": "2026-03-14_18-56-09.129", "scenes_answer_time": "2026-03-14_18-56-09.806", "colors_question_appear": "2026-03-14_18-56-11.821", "colors_answer_time": "2026-03-14_18-56-12.601"}}, "trial_12": {"glasses": {"colors": "yellow", "scenes": "living_room"}, "trial_times": {"object_appear": "2026-03-14_18-56-14.621", "object_disappear": "2026-03-14_18-56-17.634", "scenes_question_appear": "2026-03-14_18-56-20.651", "scenes_answer_time": "2026-03-14_18-56-22.351", "colors_question_appear": "2026-03-14_18-56-24.367", "colors_answer_time": "2026-03-14_18-56-25.571"}}, "trial_13": {"fan": {"colors": "yellow", "scenes": "kitchen"}, "trial_times": {"object_appear": "2026-03-14_18-56-27.598", "object_disappear": "2026-03-14_18-56-30.611", "colors_question_appear": "2026-03-14_18-56-33.628", "colors_answer_time": "2026-03-14_18-56-34.819", "scenes_question_appear": "2026-03-14_18-56-36.835", "scenes_answer_time": "2026-03-14_18-56-37.670"}}, "trial_14": {"cat": {"colors": "red", "scenes": "bathroom"}, "trial_times": {"object_appear": "2026-03-14_18-56-39.695", "object_disappear": "2026-03-14_18-56-42.708", "colors_question_appear": "2026-03-14_18-56-45.725", "colors_answer_time": "2026-03-14_18-56-46.821", "scenes_question_appear": "2026-03-14_18-56-48.837", "scenes_answer_time": "2026-03-14_18-56-49.846"}}, "trial_15": {"flower pot": {"colors": "yellow", "scenes": "living_room"}, "trial_times": {"object_appear": "2026-03-14_18-56-51.873", "object_disappear": "2026-03-14_18-56-54.886", "scenes_question_appear": "2026-03-14_18-56-57.903", "scenes_answer_time": "2026-03-14_18-56-59.195", "colors_question_appear": "2026-03-14_18-57-01.212", "colors_answer_time": "2026-03-14_18-57-02.040"}}}